simpledatasetlabeler/__init__.py
simpledatasetlabeler/commands/__init__.py
simpledatasetlabeler/commands/labeler.py
simpledatasetlabeler/frontend/asset-manifest.json
simpledatasetlabeler/frontend/index.html
simpledatasetlabeler/frontend/robots.txt
simpledatasetlabeler/frontend/static/css/main.573a9eb4.chunk.css
simpledatasetlabeler/frontend/static/css/main.573a9eb4.chunk.css.map
simpledatasetlabeler/frontend/static/js/2.15f4fd7c.chunk.js
simpledatasetlabeler/frontend/static/js/2.15f4fd7c.chunk.js.LICENSE.txt
simpledatasetlabeler/frontend/static/js/2.15f4fd7c.chunk.js.map
simpledatasetlabeler/frontend/static/js/main.285ec605.chunk.js
simpledatasetlabeler/frontend/static/js/main.285ec605.chunk.js.map
simpledatasetlabeler/frontend/static/js/runtime-main.8233b8b5.js
simpledatasetlabeler/frontend/static/js/runtime-main.8233b8b5.js.map
simpledatasetlabeler-0.1.1.dist-info/LICENSE
simpledatasetlabeler-0.1.1.dist-info/METADATA
simpledatasetlabeler-0.1.1.dist-info/WHEEL
simpledatasetlabeler-0.1.1.dist-info/entry_points.txt
simpledatasetlabeler-0.1.1.dist-info/top_level.txt
simpledatasetlabeler-0.1.1.dist-info/RECORD
