Metadata-Version: 2.1
Name: simpledatasetlabeler
Version: 0.1.1
Summary: Simple labeling tool
Home-page: https://github.com/shonohs/simpledataset_labeler
License: MIT
Platform: UNKNOWN
Classifier: Intended Audience :: Developers
Classifier: License :: OSI Approved :: MIT License
Requires-Dist: flask
Requires-Dist: simpledataset
